puyadl/__init__.py
puyadl/__main__.py
puyadl/dialog.py
puyadl/episode_parser.py
puyadl/gui.py
puyadl/scraper.py
puya_dl-1.1.2.dist-info/LICENSE
puya_dl-1.1.2.dist-info/METADATA
puya_dl-1.1.2.dist-info/WHEEL
puya_dl-1.1.2.dist-info/top_level.txt
puya_dl-1.1.2.dist-info/RECORD
