Metadata-Version: 2.1
Name: puya-dl
Version: 1.1.2
Summary: Short Python script and GUI for batch downloading PuyaSubs releases
Home-page: https://github.com/pizza61/puya-dl
Author: pizza61
Author-email: 2006mappa@protonmail.com
License: UNKNOWN
Project-URL: Bug Tracker, https://github.com/pizza61/puya-dl/issues
Platform: UNKNOWN
Classifier: Programming Language :: Python :: 3
Classifier: License :: OSI Approved :: MIT License
Classifier: Operating System :: POSIX :: Linux
Classifier: Environment :: X11 Applications :: Qt
Requires-Python: >=3.6
Requires-Dist: requests (>=2.25.1)
Requires-Dist: beautifulsoup4 (>=4.9.3)
Requires-Dist: PySide6 (>=6.0.2)
